ufoLib2/__init__.py
ufoLib2/_version.py
ufoLib2/constants.py
ufoLib2/converters.py
ufoLib2/errors.py
ufoLib2/py.typed
ufoLib2/typing.py
ufoLib2/objects/__init__.py
ufoLib2/objects/anchor.py
ufoLib2/objects/component.py
ufoLib2/objects/contour.py
ufoLib2/objects/dataSet.py
ufoLib2/objects/features.py
ufoLib2/objects/font.py
ufoLib2/objects/glyph.py
ufoLib2/objects/guideline.py
ufoLib2/objects/image.py
ufoLib2/objects/imageSet.py
ufoLib2/objects/kerning.py
ufoLib2/objects/layer.py
ufoLib2/objects/layerSet.py
ufoLib2/objects/lib.py
ufoLib2/objects/misc.py
ufoLib2/objects/point.py
ufoLib2/objects/info/__init__.py
ufoLib2/objects/info/woff.py
ufoLib2/pointPens/__init__.py
ufoLib2/pointPens/glyphPointPen.py
ufoLib2/serde/__init__.py
ufoLib2/serde/json.py
ufoLib2/serde/msgpack.py
ufoLib2/serde/util.py
ufolib2-0.18.0.dist-info/licenses/LICENSE
ufolib2-0.18.0.dist-info/METADATA
ufolib2-0.18.0.dist-info/WHEEL
ufolib2-0.18.0.dist-info/top_level.txt
ufolib2-0.18.0.dist-info/RECORD
